conformist/__init__.py
conformist/alpha_selector.py
conformist/base_cop.py
conformist/fnr_cop.py
conformist/model_vs_cop_fnr.py
conformist/output_dir.py
conformist/performance_report.py
conformist/prediction_data_preprocessor.py
conformist/prediction_dataset.py
conformist/simple_cop.py
conformist/validation_run.py
conformist/validation_trial.py
conformist-1.1.1.dist-info/LICENSE
conformist-1.1.1.dist-info/METADATA
conformist-1.1.1.dist-info/WHEEL
conformist-1.1.1.dist-info/top_level.txt
conformist-1.1.1.dist-info/RECORD
