Metadata-Version: 2.1
Name: conformist
Version: 1.1.1
Summary: Conformal prediction for machine learning classifiers
Author-email: Mariya Lysenkova Wiklander <mariya.lysenkova@medsci.uu.se>
License: MIT License
Project-URL: Homepage, https://github.com/Molmed/conformist
Keywords: machinelearning,statistics
Classifier: License :: OSI Approved :: MIT License
Classifier: Programming Language :: Python
Classifier: Programming Language :: Python :: 3
Requires-Python: >=3.8
License-File: LICENSE
Requires-Dist: numpy>=1.24.4
Requires-Dist: pandas>=2.0.3
Requires-Dist: UpSetPlot>=0.9.0
Requires-Dist: seaborn>=0.13.2
Requires-Dist: scipy>=1.10.1
Provides-Extra: dev
Requires-Dist: black; extra == "dev"
Requires-Dist: bumpver; extra == "dev"
Requires-Dist: isort; extra == "dev"
Requires-Dist: pip-tools; extra == "dev"
Requires-Dist: pytest; extra == "dev"
